ienv/__help__.py
ienv/__init__.py
ienv/__main__.py
ienv/settings.py
ienv-0.1.1.dist-info/METADATA
ienv-0.1.1.dist-info/WHEEL
ienv-0.1.1.dist-info/entry_points.txt
ienv-0.1.1.dist-info/top_level.txt
ienv-0.1.1.dist-info/RECORD
