Metadata-Version: 2.1
Name: ienv
Version: 0.1.1
Summary: Create virtual environment of project.
Home-page: https://github.com/536/ienv
Author: JiangHui
License: MIT
Platform: UNKNOWN
Classifier: Programming Language :: Python :: 3.6
Classifier: Programming Language :: Python :: 3.7
Classifier: Programming Language :: Python :: 3.8
Classifier: Programming Language :: Python :: 3.9
Classifier: License :: OSI Approved :: MIT License
Requires-Python: >=3.6
